graphite_exporter/__init__.py
graphite_exporter/__main__.py
graphite_exporter/collector.py
graphite_exporter/types.py
graphite_exporter/utils.py
graphite_exporter-1.2.2.dist-info/LICENSE
graphite_exporter-1.2.2.dist-info/METADATA
graphite_exporter-1.2.2.dist-info/WHEEL
graphite_exporter-1.2.2.dist-info/RECORD
