Metadata-Version: 2.1
Name: graphite-exporter
Version: 1.2.2
Summary: Prometheus Graphite Exporter
Home-page: https://github.com/so1n/graphite_exporter
License: Apache Software License
Author: So1n
Author-email: so1n897046026@gamil.com
Requires-Python: >=3.7,<4.0
Classifier: License :: Other/Proprietary License
Classifier: Programming Language :: Python :: 3
Classifier: Programming Language :: Python :: 3.7
Classifier: Programming Language :: Python :: 3.8
Classifier: Programming Language :: Python :: 3.9
Classifier: Programming Language :: Python :: 3.10
Classifier: Programming Language :: Python :: 3.11
Requires-Dist: APScheduler (==3.6.3)
Requires-Dist: PyYAML (>=5.4.1,<6.0.0)
Requires-Dist: prometheus-client (==0.7.1)
Requires-Dist: requests (>=2.25.1,<3.0.0)
Requires-Dist: typing-extensions (>=4.5.0,<5.0.0)
Project-URL: Repository, https://github.com/so1n/graphite_exporter
